getan/__init__.py
getan/backend.py
getan/config.py
getan/controller.py
getan/main.py
getan/nodes.py
getan/project.py
getan/resources.py
getan/states.py
getan/template.py
getan/utils.py
getan/view.py
getan/walker.py
getan/templates/wochenbericht
getan/templates/wochenfazit
getan/templates/wochentabelle1
getan/templates/zeiterfassung
getan/templates/zeiterfassung-hierarchy1
getan/templates/zeiterfassung-hierarchy2
getan/templates/zeiterfassung2
getan-3.7.1.data/scripts/convert-projects
getan-3.7.1.data/scripts/getan-daily-report
getan-3.7.1.data/scripts/getan-report
getan-3.7.1.dist-info/licenses/LICENSE
getan-3.7.1.dist-info/METADATA
getan-3.7.1.dist-info/WHEEL
getan-3.7.1.dist-info/entry_points.txt
getan-3.7.1.dist-info/top_level.txt
getan-3.7.1.dist-info/RECORD
