Metadata-Version: 2.4
Name: getan
Version: 3.7.1
Summary: Terminal based time-tracking and reporting tool; comparable to 'worklog'.
Home-page: https://heptapod.host/intevation/getan
Maintainer: magnus.schieder
Maintainer-email: magnus.schieder@intevation.de
License: GPLv3+
Classifier: Development Status :: 5 - Production/Stable
Classifier: Topic :: Utilities
Classifier: Environment :: Console
Classifier: Intended Audience :: Developers
Classifier: Intended Audience :: End Users/Desktop
Classifier: License :: OSI Approved :: GNU General Public License v3 or later (GPLv3+)
Classifier: Operating System :: POSIX
Classifier: Programming Language :: Python :: 3.4
Requires-Python: >=3.4
License-File: LICENSE
Requires-Dist: jinja2
Requires-Dist: urwid>=1.1.2
Dynamic: classifier
Dynamic: description
Dynamic: description-content-type
Dynamic: home-page
Dynamic: license
Dynamic: license-file
Dynamic: maintainer
Dynamic: maintainer-email
Dynamic: requires-dist
Dynamic: requires-python
Dynamic: summary
